pyclg/__init__.py
pyclg/pyclg.py
pyclg-1.0.0.dist-info/WHEEL
pyclg-1.0.0.dist-info/METADATA
pyclg-1.0.0.dist-info/RECORD
